flask_fast/__init__.py
flask_fast/api.py
flask_fast/swagger.py
flask_fast/utils.py
flask_fast-0.0.1.dev0.dist-info/LICENSE
flask_fast-0.0.1.dev0.dist-info/METADATA
flask_fast-0.0.1.dev0.dist-info/WHEEL
flask_fast-0.0.1.dev0.dist-info/top_level.txt
flask_fast-0.0.1.dev0.dist-info/RECORD
